MANIFEST.in
README.rst
setup.py
collective/__init__.py
collective.pygal.core.egg-info/PKG-INFO
collective.pygal.core.egg-info/SOURCES.txt
collective.pygal.core.egg-info/dependency_links.txt
collective.pygal.core.egg-info/entry_points.txt
collective.pygal.core.egg-info/namespace_packages.txt
collective.pygal.core.egg-info/not-zip-safe
collective.pygal.core.egg-info/requires.txt
collective.pygal.core.egg-info/top_level.txt
collective/pygal/__init__.py
collective/pygal/core/__init__.py
collective/pygal/core/configure.zcml
collective/pygal/core/interfaces.py
collective/pygal/core/tests.py
collective/pygal/core/version.txt
collective/pygal/core/browser/__init__.py
collective/pygal/core/browser/configure.zcml
collective/pygal/core/browser/resources/graph.css
collective/pygal/core/browser/resources/graph.js
collective/pygal/core/profiles/default/browserlayer.xml
collective/pygal/core/profiles/default/cssregistry.xml
collective/pygal/core/profiles/default/jsregistry.xml
collective/pygal/core/profiles/default/metadata.xml
docs/HISTORY.txt
docs/INSTALL.txt
docs/LICENSE.txt