Metadata-Version: 1.0
Name: collective.pygal.core
Version: 0.1
Summary: Pygal dynamic SVG charting library integration for plone
Home-page: https://github.com/collective/collective.pygal.core
Author: Christian Ledermann
Author-email: christian.ledermann@gmail.com
License: GPL
Platform: UNKNOWN
Classifier: Framework :: Plone
Classifier: Framework :: Plone :: 4.0
Classifier: Framework :: Plone :: 4.1
Classifier: Intended Audience :: Developers
Classifier: Environment :: Web Environment
Classifier: License :: OSI Approved :: GNU General Public License (GPL)
Classifier: Programming Language :: Python :: 2
Classifier: Topic :: Multimedia :: Graphics :: Presentation
